PyMyMethod/__init__.py
PyMyMethod/code/__init__.py
PyMyMethod/code/file_control.py
PyMyMethod/code/mouse_control.py
PyMyMethod/code/regedit.py
PyMyMethod/code/screen_control.py
PyMyMethod/code/system_control.py
PyMyMethod/code/terminal_command.py
PyMyMethod/doc/__init__.py
PyMyMethod/doc/method_doc.py
PyMyMethod-1.0.6.dist-info/METADATA
PyMyMethod-1.0.6.dist-info/WHEEL
PyMyMethod-1.0.6.dist-info/top_level.txt
PyMyMethod-1.0.6.dist-info/RECORD
